odoo/addons/partner_invoicing_mode_monthly/README.rst
odoo/addons/partner_invoicing_mode_monthly/__init__.py
odoo/addons/partner_invoicing_mode_monthly/__manifest__.py
odoo/addons/partner_invoicing_mode_monthly/data/ir_cron.xml
odoo/addons/partner_invoicing_mode_monthly/data/queue_job_data.xml
odoo/addons/partner_invoicing_mode_monthly/i18n/es.po
odoo/addons/partner_invoicing_mode_monthly/i18n/hr.po
odoo/addons/partner_invoicing_mode_monthly/i18n/it.po
odoo/addons/partner_invoicing_mode_monthly/i18n/partner_invoicing_mode_monthly.pot
odoo/addons/partner_invoicing_mode_monthly/models/__init__.py
odoo/addons/partner_invoicing_mode_monthly/models/res_company.py
odoo/addons/partner_invoicing_mode_monthly/models/res_config_settings.py
odoo/addons/partner_invoicing_mode_monthly/models/res_partner.py
odoo/addons/partner_invoicing_mode_monthly/models/sale_order.py
odoo/addons/partner_invoicing_mode_monthly/readme/CONTRIBUTORS.md
odoo/addons/partner_invoicing_mode_monthly/readme/CREDITS.md
odoo/addons/partner_invoicing_mode_monthly/readme/DESCRIPTION.md
odoo/addons/partner_invoicing_mode_monthly/readme/INSTALL.md
odoo/addons/partner_invoicing_mode_monthly/static/description/icon.png
odoo/addons/partner_invoicing_mode_monthly/static/description/index.html
odoo/addons/partner_invoicing_mode_monthly/tests/__init__.py
odoo/addons/partner_invoicing_mode_monthly/tests/test_invoice_mode_monthly.py
odoo/addons/partner_invoicing_mode_monthly/tests/test_invoice_mode_monthly_is_it_today.py
odoo/addons/partner_invoicing_mode_monthly/views/res_config_settings_views.xml
odoo_addon_partner_invoicing_mode_monthly-18.0.1.0.0.2.dist-info/METADATA
odoo_addon_partner_invoicing_mode_monthly-18.0.1.0.0.2.dist-info/WHEEL
odoo_addon_partner_invoicing_mode_monthly-18.0.1.0.0.2.dist-info/top_level.txt
odoo_addon_partner_invoicing_mode_monthly-18.0.1.0.0.2.dist-info/RECORD
